sentieoaws/__init__.py
sentieoaws/constants.py
sentieoaws/py.typed
sentieoaws/s3api.py
sentieoaws/sentieo_aws_base.py
sentieoaws/snsapi.py
sentieoaws/sqsapi.py
sentieoaws-0.0.6.dist-info/METADATA
sentieoaws-0.0.6.dist-info/WHEEL
sentieoaws-0.0.6.dist-info/entry_points.txt
sentieoaws-0.0.6.dist-info/RECORD
