Metadata-Version: 2.1
Name: sentieoaws
Version: 0.0.6
Summary: sentieoaws
Author: shubham-sentieo
Author-email: shubham.bansal@sentieo.com
Requires-Python: >=3.8,<4.0
Classifier: Programming Language :: Python :: 3
Classifier: Programming Language :: Python :: 3.8
Classifier: Programming Language :: Python :: 3.9
Classifier: Programming Language :: Python :: 3.10
Classifier: Programming Language :: Python :: 3.11
Classifier: Programming Language :: Python :: 3.12
Requires-Dist: Brotli (>=1.0.9,<2.0.0)
Requires-Dist: localstack-client (>=1.35,<2.0)
Requires-Dist: python-magic (>=0.4.26,<0.5.0)
Requires-Dist: pyupgrade (>=2.32.1,<3.0.0)
